setup.cfg
setup.py
specularity_removal/__init__.py
specularity_removal/homography.py
specularity_removal/main.py
specularity_removal.egg-info/PKG-INFO
specularity_removal.egg-info/SOURCES.txt
specularity_removal.egg-info/dependency_links.txt
specularity_removal.egg-info/top_level.txt