Metadata-Version: 1.1
Name: specularity-removal
Version: 0.1
Summary: Implements specular removal in images captured from various view points
Home-page: https://github.com/gmichaeljaison/specularity-removal
Author: Michael Jaison Gnanasekar, Shreyas Joshi
Author-email: gmichaeljaison@gmail.com, shreyasvj25@gmail.com
License: UNKNOWN
Download-URL: https://github.com/gmichaeljaison/specularity-removal/tarball/0.1
Keywords: computer vision,image processing,specularity-removal,highlights,homography
Platform: UNKNOWN
Classifier: Development Status :: 3 - AlphaTopic :: UtilitiesLicense :: BSD License
Requires: numpy
Requires: cv2
